setup.cfg
setup.py
fi_va295.egg-info/PKG-INFO
fi_va295.egg-info/SOURCES.txt
fi_va295.egg-info/dependency_links.txt
fi_va295.egg-info/not-zip-safe
fi_va295.egg-info/top_level.txt
fi_va295/circle/__init__.py
fi_va295/circle/code.py
fi_va295/square/__init__.py
fi_va295/square/code.py
fi_va295/triangle/__init__.py
fi_va295/triangle/code.py