Metadata-Version: 2.1
Name: fi-va295
Version: 0.0
Summary: circle, tiangle, square
Author-email: vanisimov2905@gmail.com
